api/__init__.py
api/api.py
api/exceptions.py
api/objects.py
disweb.py-1.0.0.dist-info/LICENSE
disweb.py-1.0.0.dist-info/METADATA
disweb.py-1.0.0.dist-info/WHEEL
disweb.py-1.0.0.dist-info/top_level.txt
disweb.py-1.0.0.dist-info/RECORD
