Metadata-Version: 2.1
Name: disweb.py
Version: 1.0.0
Summary: A simple python wrapper for the disweb api.
Home-page: https://github.com/InvalidLenni/disweb.py
Author: InvalidLenni
License: MIT
Project-URL: Documentation, https://invalidlenni.gitbook.io/disweb.py/
Project-URL: Issue Tracker, https://github.com/InvalidLenni/disweb.py/issues/
Platform: UNKNOWN
Classifier: Development Status :: 5 - Production/Stable
Classifier: Intended Audience :: Developers
Classifier: License :: OSI Approved :: MIT License
Classifier: Programming Language :: Python :: 3.8
Classifier: Programming Language :: Python :: 3.9
Classifier: Programming Language :: Python :: 3.10
Requires-Python: >=3.8
License-File: LICENSE
Requires-Dist: aiohttp (<3.8.0,>=3.6.0)
Requires-Dist: setuptools (>=60.4.0)
